cabalgata
cabalgata/silla
cabalgata/silla/util
